wnox/__init__.py
wnox-1.1.0.dist-info/LICENSE.txt
wnox-1.1.0.dist-info/METADATA
wnox-1.1.0.dist-info/WHEEL
wnox-1.1.0.dist-info/top_level.txt
wnox-1.1.0.dist-info/RECORD
